smartship/__init__.py
smartship/_client.py
smartship/constants.py
smartship/exceptions.py
smartship/objects.py
smartship/schemas.py
smartship/shipments.py
smartship/carriers/__init__.py
smartship/carriers/posti.py
smartship-1.2.0.dist-info/DESCRIPTION.rst
smartship-1.2.0.dist-info/LICENSE.txt
smartship-1.2.0.dist-info/METADATA
smartship-1.2.0.dist-info/RECORD
smartship-1.2.0.dist-info/WHEEL
smartship-1.2.0.dist-info/metadata.json
smartship-1.2.0.dist-info/top_level.txt
