Metadata-Version: 2.0
Name: smartship
Version: 1.2.0
Summary: Posti SmartShip API
Home-page: https://github.com/andersinno/smartship
Author: Anders Innovations
Author-email: support@anders.fi
License: MIT
Download-URL: https://github.com/andersinno/smartship/releases
Keywords: smartship,posti
Platform: UNKNOWN
Classifier: Development Status :: 5 - Production/Stable
Classifier: Intended Audience :: Developers
Classifier: License :: OSI Approved :: MIT License
Classifier: Programming Language :: Python
Classifier: Programming Language :: Python :: 2
Classifier: Programming Language :: Python :: 2.7
Classifier: Programming Language :: Python :: 3
Classifier: Programming Language :: Python :: 3.4
Classifier: Programming Language :: Python :: 3.5
Classifier: Programming Language :: Python :: 3.6
Classifier: Topic :: Software Development :: Libraries :: Python Modules
Requires-Dist: attrs (<18,>=17.3.0)
Requires-Dist: enum34 (>=1.1.6,<2)
Requires-Dist: jsonschema (<3,>=2.0)
Requires-Dist: requests (>=2.11.1,<3)
Requires-Dist: simplejson (<4,>=3.10.0)
